odoo/addons/product_packaging_type/README.rst
odoo/addons/product_packaging_type/__init__.py
odoo/addons/product_packaging_type/__manifest__.py
odoo/addons/product_packaging_type/data/product_packaging_type.xml
odoo/addons/product_packaging_type/i18n/es.po
odoo/addons/product_packaging_type/i18n/nl.po
odoo/addons/product_packaging_type/i18n/product_packaging_type.pot
odoo/addons/product_packaging_type/models/__init__.py
odoo/addons/product_packaging_type/models/product_packaging_type.py
odoo/addons/product_packaging_type/readme/CONTRIBUTORS.rst
odoo/addons/product_packaging_type/readme/CREDITS.rst
odoo/addons/product_packaging_type/readme/DESCRIPTION.rst
odoo/addons/product_packaging_type/readme/USAGE.rst
odoo/addons/product_packaging_type/security/ir.model.access.csv
odoo/addons/product_packaging_type/static/description/icon.png
odoo/addons/product_packaging_type/static/description/index.html
odoo/addons/product_packaging_type/views/product_packaging_type_view.xml
odoo/addons/product_packaging_type/views/product_packaging_view.xml
odoo14_addon_product_packaging_type-14.0.0.2.0.dist-info/METADATA
odoo14_addon_product_packaging_type-14.0.0.2.0.dist-info/WHEEL
odoo14_addon_product_packaging_type-14.0.0.2.0.dist-info/top_level.txt
odoo14_addon_product_packaging_type-14.0.0.2.0.dist-info/RECORD
